{
  "ALBUM_SPECS": [
    {
      "title": "2015",
      "photoCount": 101
    },
    {
      "title": "Cabo2018",
      "photoCount": 14
    },
    {
      "title": "2 days in San Jose and Los Altos Hills",
      "photoCount": 14
    },
    {
      "title": "Bend/Oakridge June 2018",
      "photoCount": 8
    },
    {
      "title": "Iceland/Southern Spain March 2018",
      "photoCount": 1
    },
    {
      "title": "Test",
      "photoCount": 4
    },
    {
      "title": "New Zealand -Abel Tasman",
      "photoCount": 5
    },
    {
      "title": "Summer 2018",
      "photoCount": 53
    },
    {
      "title": "ToPrintOct2019",
      "photoCount": 20
    },
    {
      "title": "Lori-Shared#2",
      "photoCount": 114
    },
    {
      "title": "test2",
      "photoCount": 114
    },
    {
      "title": "Paris/Spain/Portugal May 2018",
      "photoCount": 195
    },
    {
      "title": " ",
      "photoCount": 80
    },
    {
      "title": "Norway 2017",
      "photoCount": 87
    },
    {
      "title": "Joel 2017",
      "photoCount": 13
    },
    {
      "title": "Whacha eating?",
      "photoCount": 138
    },
    {
      "title": "Thailand",
      "photoCount": 5
    },
    {
      "title": "Schlitzenblitzen",
      "photoCount": 541
    },
    {
      "title": "Sam's Uploads",
      "photoCount": 357
    },
    {
      "title": "Year2016",
      "photoCount": 379
    },
    {
      "title": "Family 2016",
      "photoCount": 42
    },
    {
      "title": "New Orleans 2016",
      "photoCount": 26
    },
    {
      "title": "Trip to New Orleans",
      "photoCount": 22
    },
    {
      "title": "Joel's uploads",
      "photoCount": 410
    },
    {
      "title": "Print",
      "photoCount": 22
    },
    {
      "title": "Europe 2016",
      "photoCount": 63
    },
    {
      "title": "Year2015",
      "photoCount": 1050
    },
    {
      "title": "Scuba",
      "photoCount": 77
    },
    {
      "title": "Europe 2015",
      "photoCount": 69
    },
    {
      "title": "Croatia & Slovenia 2015",
      "photoCount": 56
    },
    {
      "title": "Year2014",
      "photoCount": 331
    },
    {
      "title": "Jewish Stuff",
      "photoCount": 100
    },
    {
      "title": "Too Cute",
      "photoCount": 36
    },
    {
      "title": "Alaska 2014",
      "photoCount": 44
    },
    {
      "title": "Year2013",
      "photoCount": 168
    },
    {
      "title": "Aspen/Southwest 2012",
      "photoCount": 47
    },
    {
      "title": "Israel-Joel & Rachel ",
      "photoCount": 13
    },
    {
      "title": "New Zealand December 2012",
      "photoCount": 42
    },
    {
      "title": "Kathy - New Zealand 2012",
      "photoCount": 44
    },
    {
      "title": "Year2012",
      "photoCount": 167
    },
    {
      "title": "Barcelona/Italy November 2012",
      "photoCount": 31
    },
    {
      "title": "Year2008",
      "photoCount": 22
    }
  ]
}